.gitignore
MANIFEST.in
README.rst
bootstrap.py
buildout.cfg
setup.py
collective/__init__.py
collective.js.masonry.egg-info/PKG-INFO
collective.js.masonry.egg-info/SOURCES.txt
collective.js.masonry.egg-info/dependency_links.txt
collective.js.masonry.egg-info/entry_points.txt
collective.js.masonry.egg-info/namespace_packages.txt
collective.js.masonry.egg-info/not-zip-safe
collective.js.masonry.egg-info/requires.txt
collective.js.masonry.egg-info/top_level.txt
collective/js/__init__.py
collective/js/masonry/__init__.py
collective/js/masonry/configure.zcml
collective/js/masonry/upgrades.py
collective/js/masonry/upgrades.zcml
collective/js/masonry/profiles/default/jsregistry.xml
collective/js/masonry/profiles/default/metadata.xml
collective/js/masonry/resources/jquery.masonry.js
collective/js/masonry/resources/jquery.masonry.min.js
docs/HISTORY.txt