Metadata-Version: 1.0
Name: collective.js.masonry
Version: 1.0
Summary: Register jquery.massonry to Plone resource registry
Home-page: https://github.com/collective/collective.js.masonry
Author: JeanMichel FRANCOIS aka toutpt
Author-email: toutpt@gmail.com
License: GPL
Keywords: plone javascripts masonry
Platform: UNKNOWN
Classifier: Environment :: Web Environment
Classifier: License :: OSI Approved :: GNU General Public License (GPL)
Classifier: Operating System :: OS Independent
Classifier: Framework :: Plone
Classifier: Framework :: Plone :: 4.0
Classifier: Framework :: Plone :: 4.1
Classifier: Framework :: Plone :: 4.2
Classifier: Programming Language :: Python
